main.py
crudzilla-0.1.0.dist-info/METADATA
crudzilla-0.1.0.dist-info/WHEEL
crudzilla-0.1.0.dist-info/entry_points.txt
crudzilla-0.1.0.dist-info/RECORD
