Metadata-Version: 2.4
Name: crudzilla
Version: 0.1.0
Summary: Generate Pydantic models and FastCRUD routers from database schema
Author: Andrew Maguire
License-Expression: MIT
Keywords: code-generation,crud,database,fastapi,postgresql,pydantic,sqlalchemy
Classifier: Development Status :: 4 - Beta
Classifier: Framework :: FastAPI
Classifier: Intended Audience :: Developers
Classifier: License :: OSI Approved :: MIT License
Classifier: Operating System :: OS Independent
Classifier: Programming Language :: Python :: 3
Classifier: Programming Language :: Python :: 3.10
Classifier: Programming Language :: Python :: 3.11
Classifier: Programming Language :: Python :: 3.12
Classifier: Topic :: Database
Classifier: Topic :: Software Development :: Code Generators
Classifier: Typing :: Typed
Requires-Python: >=3.10
Requires-Dist: fastcrud>=0.15.0
Requires-Dist: sqlacodegen>=3.0.0
Requires-Dist: supabase-pydantic>=0.14.0
Provides-Extra: dev
Requires-Dist: mypy>=1.0; extra == 'dev'
Requires-Dist: pytest>=7.0; extra == 'dev'
Requires-Dist: ruff>=0.1.0; extra == 'dev'
